snmp_cmds/__init__.py
snmp_cmds/api.py
snmp_cmds/commands.py
snmp_cmds/exceptions.py
snmp_cmds/helpers.py
snmp_cmds-1.0.dist-info/DESCRIPTION.rst
snmp_cmds-1.0.dist-info/LICENSE.txt
snmp_cmds-1.0.dist-info/METADATA
snmp_cmds-1.0.dist-info/RECORD
snmp_cmds-1.0.dist-info/WHEEL
snmp_cmds-1.0.dist-info/metadata.json
snmp_cmds-1.0.dist-info/top_level.txt
