Metadata-Version: 2.0
Name: snmp-cmds
Version: 1.0
Summary: A python wrapper around the Net-SNMP command line utilities
Home-page: https://github.com/alextremblay/snmp-cmds
Author: Alex Tremblay
Author-email: alextremblay@github.com
License: MIT
Platform: UNKNOWN
Classifier: Development Status :: 5 - Production/Stable
Classifier: Intended Audience :: System Administrators
Classifier: Intended Audience :: Telecommunications Industry
Classifier: Topic :: Software Development :: Libraries :: Python Modules
Classifier: Topic :: System :: Networking
Classifier: Topic :: System :: Systems Administration
Classifier: License :: OSI Approved :: MIT License
Classifier: Operating System :: MacOS
Classifier: Operating System :: Microsoft
Classifier: Operating System :: POSIX
Classifier: Operating System :: POSIX :: Linux
Classifier: Operating System :: Unix
Classifier: Programming Language :: Python :: 3
Classifier: Programming Language :: Python :: 3.5
Provides-Extra: test
Requires-Dist: pytest; extra == 'test'
Requires-Dist: snmpsim; extra == 'test'
